minipcn/__init__.py
minipcn/sampler.py
minipcn/step.py
minipcn/utils.py
minipcn-0.1.1.dist-info/licenses/LICENSE
minipcn-0.1.1.dist-info/METADATA
minipcn-0.1.1.dist-info/WHEEL
minipcn-0.1.1.dist-info/top_level.txt
minipcn-0.1.1.dist-info/RECORD
